README.md
disputer-config.yaml
tellor_disputables/__init__.py
tellor_disputables/alerts.py
tellor_disputables/cli.py
tellor_disputables/config.py
tellor_disputables/data.py
tellor_disputables/disputer.py
tellor_disputables/utils.py
vars.example.sh
tellor_disputables-1.4.2.dist-info/METADATA
tellor_disputables-1.4.2.dist-info/WHEEL
tellor_disputables-1.4.2.dist-info/entry_points.txt
tellor_disputables-1.4.2.dist-info/RECORD
