Metadata-Version: 2.1
Name: tellor-disputables
Version: 1.4.2
Summary: dashboard & text alerts for disputable values reported to Tellor oracles
License: MIT
Author: tallywiesenberg
Author-email: info@tellor.io
Requires-Python: >=3.9,<3.11
Classifier: License :: OSI Approved :: MIT License
Classifier: Programming Language :: Python :: 3
Classifier: Programming Language :: Python :: 3.9
Classifier: Programming Language :: Python :: 3.10
Requires-Dist: click (>=8.1.3,<9.0.0)
Requires-Dist: pandas (>=1.4.1,<2.0.0)
Requires-Dist: pydantic (>=1.10.2,<2.0.0)
Requires-Dist: pytest-asyncio (>=0.19.0,<0.20.0)
Requires-Dist: python-box (>=7.0.1,<8.0.0)
Requires-Dist: tabulate (>=0.8.9,<0.9.0)
Requires-Dist: telliot-feeds (>=0.1.10,<0.2.0)
Requires-Dist: twilio (>=7.7.0,<8.0.0)
Requires-Dist: web3 (>=5.27.0,<6.0.0)
